datadog_pandas/__init__.py
datadog_pandas/query.py
datadog_pandas/ipython/__init__.py
datadog_pandas/ipython/magic.py
datadog_pandas-0.1.0.dist-info/LICENSE
datadog_pandas-0.1.0.dist-info/METADATA
datadog_pandas-0.1.0.dist-info/WHEEL
datadog_pandas-0.1.0.dist-info/top_level.txt
datadog_pandas-0.1.0.dist-info/RECORD
