Metadata-Version: 2.1
Name: datadog-pandas
Version: 0.1.0
Summary: Pandas integration for Datadog
Home-page: https://github.com/LemontechSA/datadog-pandas
Classifier: Programming Language :: Python :: 3
Classifier: License :: OSI Approved :: MIT License
Classifier: Operating System :: OS Independent
Requires-Python: >=3.6
License-File: LICENSE
